wrds2pg/__init__.py
wrds2pg/wrds2pg.py
wrds2pg-1.0.35.dist-info/licenses/LICENCE
wrds2pg-1.0.35.dist-info/METADATA
wrds2pg-1.0.35.dist-info/WHEEL
wrds2pg-1.0.35.dist-info/top_level.txt
wrds2pg-1.0.35.dist-info/RECORD
