Metadata-Version: 2.4
Name: wrds2pg
Version: 1.0.35
Summary: Convert WRDS or local SAS data to PostgreSQL, parquet, or CSV.
Home-page: https://github.com/iangow/wrds2pg/
Author: Ian Gow
Author-email: iandgow@gmail.com
Classifier: Programming Language :: Python :: 3
Classifier: License :: OSI Approved :: MIT License
Classifier: Operating System :: OS Independent
Requires-Python: >=3
License-File: LICENCE
Requires-Dist: pandas
Requires-Dist: sqlalchemy>=2.0.0
Requires-Dist: paramiko
Requires-Dist: psycopg[binary]
Requires-Dist: pyarrow
Requires-Dist: duckdb
Dynamic: author
Dynamic: author-email
Dynamic: classifier
Dynamic: description
Dynamic: description-content-type
Dynamic: home-page
Dynamic: license-file
Dynamic: requires-dist
Dynamic: requires-python
Dynamic: summary
